hollihop_api_client/__init__.py
hollihop_api_client/categories.py
hollihop_api_client/api/__init__.py
hollihop_api_client/api/abc.py
hollihop_api_client/api/api.py
hollihop_api_client/base/__init__.py
hollihop_api_client/base/category.py
hollihop_api_client/methods/__init__.py
hollihop_api_client/methods/clients.py
hollihop_api_client/methods/disciplines.py
hollihop_api_client/methods/ed_unit_students.py
hollihop_api_client/methods/ed_units.py
hollihop_api_client/methods/leads.py
hollihop_api_client/methods/learning_types.py
hollihop_api_client/methods/levels.py
hollihop_api_client/methods/locations.py
hollihop_api_client/methods/offices.py
hollihop_api_client/models/requests.py
hollihop_api_client/tools/__init__.py
hollihop_api_client/venv/bin/rst2html.py
hollihop_api_client/venv/bin/rst2html4.py
hollihop_api_client/venv/bin/rst2html5.py
hollihop_api_client/venv/bin/rst2latex.py
hollihop_api_client/venv/bin/rst2man.py
hollihop_api_client/venv/bin/rst2odt.py
hollihop_api_client/venv/bin/rst2odt_prepstyles.py
hollihop_api_client/venv/bin/rst2pseudoxml.py
hollihop_api_client/venv/bin/rst2s5.py
hollihop_api_client/venv/bin/rst2xetex.py
hollihop_api_client/venv/bin/rst2xml.py
hollihop_api_client/venv/bin/rstpep2html.py
hollihop_api_client-0.0.24.dist-info/LICENSE
hollihop_api_client-0.0.24.dist-info/METADATA
hollihop_api_client-0.0.24.dist-info/WHEEL
hollihop_api_client-0.0.24.dist-info/top_level.txt
hollihop_api_client-0.0.24.dist-info/RECORD
