Metadata-Version: 2.1
Name: hollihop_api_client
Version: 0.0.24
Summary: This library helps you easily create a python application with Hollihop API
Author-email: Nicholas Maltsev <nmmaltsev@outlook.com>
Project-URL: Homepage, https://github.com/nicholasChieftain/hollihop_api_client/
Project-URL: Bug Tracker, https://github.com/nicholasChieftain/hollihop_api_client/issues
Classifier: Programming Language :: Python :: 3.10
Classifier: License :: OSI Approved :: MIT License
Classifier: Operating System :: MacOS
Classifier: Operating System :: POSIX :: Linux
Requires-Python: >=3.10
License-File: LICENSE
Requires-Dist: phonenumbers >=8.3.11
Requires-Dist: requests >=2.30.0
